setup.py
depends/Depends.py
depends/Errors.py
depends/__init__.py
depends.egg-info/PKG-INFO
depends.egg-info/SOURCES.txt
depends.egg-info/dependency_links.txt
depends.egg-info/top_level.txt
test/__init__.py
test/test.py