Metadata-Version: 1.1
Name: depends
Version: 1.7
Summary: A pure-python dependency linker and checker
Home-page: https://bitbucket.com/sys-git/depends
Author: Francis Horsman
Author-email: francis.horsman@gmail.com
License: GNU General Public License
Platform: UNKNOWN
Classifier: Development Status :: 5 - Production/Stable
Classifier: Intended Audience :: Developers
Classifier: License :: OSI Approved :: GNU General Public License v3 (GPLv3)
Classifier: Operating System :: OS Independent
Classifier: Programming Language :: Python
Classifier: Topic :: Communications
